mcp_server_tree_sitter/__init__.py
mcp_server_tree_sitter/__main__.py
mcp_server_tree_sitter/api.py
mcp_server_tree_sitter/config.py
mcp_server_tree_sitter/context.py
mcp_server_tree_sitter/di.py
mcp_server_tree_sitter/exceptions.py
mcp_server_tree_sitter/logging_config.py
mcp_server_tree_sitter/server.py
mcp_server_tree_sitter/bootstrap/__init__.py
mcp_server_tree_sitter/bootstrap/logging_bootstrap.py
mcp_server_tree_sitter/cache/__init__.py
mcp_server_tree_sitter/cache/parser_cache.py
mcp_server_tree_sitter/capabilities/__init__.py
mcp_server_tree_sitter/capabilities/server_capabilities.py
mcp_server_tree_sitter/language/__init__.py
mcp_server_tree_sitter/language/query_templates.py
mcp_server_tree_sitter/language/registry.py
mcp_server_tree_sitter/language/templates/__init__.py
mcp_server_tree_sitter/language/templates/apl.py
mcp_server_tree_sitter/language/templates/c.py
mcp_server_tree_sitter/language/templates/cpp.py
mcp_server_tree_sitter/language/templates/go.py
mcp_server_tree_sitter/language/templates/java.py
mcp_server_tree_sitter/language/templates/javascript.py
mcp_server_tree_sitter/language/templates/julia.py
mcp_server_tree_sitter/language/templates/kotlin.py
mcp_server_tree_sitter/language/templates/python.py
mcp_server_tree_sitter/language/templates/rust.py
mcp_server_tree_sitter/language/templates/swift.py
mcp_server_tree_sitter/language/templates/typescript.py
mcp_server_tree_sitter/models/__init__.py
mcp_server_tree_sitter/models/ast.py
mcp_server_tree_sitter/models/ast_cursor.py
mcp_server_tree_sitter/models/project.py
mcp_server_tree_sitter/prompts/__init__.py
mcp_server_tree_sitter/prompts/code_patterns.py
mcp_server_tree_sitter/testing/__init__.py
mcp_server_tree_sitter/testing/pytest_diagnostic.py
mcp_server_tree_sitter/tools/__init__.py
mcp_server_tree_sitter/tools/analysis.py
mcp_server_tree_sitter/tools/ast_operations.py
mcp_server_tree_sitter/tools/debug.py
mcp_server_tree_sitter/tools/file_operations.py
mcp_server_tree_sitter_extra-0.0.1.dist-info/METADATA
mcp_server_tree_sitter_extra-0.0.1.dist-info/WHEEL
mcp_server_tree_sitter_extra-0.0.1.dist-info/entry_points.txt
mcp_server_tree_sitter_extra-0.0.1.dist-info/licenses/LICENSE
mcp_server_tree_sitter_extra-0.0.1.dist-info/licenses/NOTICE
mcp_server_tree_sitter_extra-0.0.1.dist-info/RECORD
